CHANGELOG.txt
LICENCE.txt
MANIFEST.in
README.txt
setup.py
Calculator/__init__.py
dist/pydevtoolkit-0.0.3/pydevtoolkit-0.0.3/CHANGELOG.txt
dist/pydevtoolkit-0.0.3/pydevtoolkit-0.0.3/LICENCE.txt
dist/pydevtoolkit-0.0.3/pydevtoolkit-0.0.3/README.txt
dist/pydevtoolkit-0.0.3/pydevtoolkit-0.0.3/setup.py
dist/pydevtoolkit-0.0.3/pydevtoolkit-0.0.3/pydevkit/Calculator/__init__.py
dist/pydevtoolkit-0.0.3/pydevtoolkit-0.0.3/pydevtoolkit.egg-info/SOURCES.txt
dist/pydevtoolkit-0.0.3/pydevtoolkit-0.0.3/pydevtoolkit.egg-info/dependency_links.txt
dist/pydevtoolkit-0.0.3/pydevtoolkit-0.0.3/pydevtoolkit.egg-info/top_level.txt
dist/pydevtoolkit-0.0.3/pydevtoolkit-0.0.3/pytoolkit.egg-info/SOURCES.txt
dist/pydevtoolkit-0.0.3/pydevtoolkit-0.0.3/pytoolkit.egg-info/dependency_links.txt
dist/pydevtoolkit-0.0.3/pydevtoolkit-0.0.3/pytoolkit.egg-info/top_level.txt
dist/pydevtoolkit-0.0.3/pydevtoolkit-0.0.3/venv/Lib/site-packages/easy_install.py
dist/pydevtoolkit-0.0.3/pydevtoolkit-0.0.3/venv/Lib/site-packages/pyparsing.py
dist/pydevtoolkit-0.0.3/pydevtoolkit-0.0.3/venv/Lib/site-packages/six.py
dist/pydevtoolkit-0.0.3/pydevtoolkit-0.0.3/venv/Lib/site-packages/Pygments-2.7.2.dist-info/entry_points.txt
dist/pydevtoolkit-0.0.3/pydevtoolkit-0.0.3/venv/Lib/site-packages/Pygments-2.7.2.dist-info/top_level.txt
dist/pydevtoolkit-0.0.3/pydevtoolkit-0.0.3/venv/Lib/site-packages/_distutils_hack/__init__.py
dist/pydevtoolkit-0.0.3/pydevtoolkit-0.0.3/venv/Lib/site-packages/_distutils_hack/override.py
dist/pydevtoolkit-0.0.3/pydevtoolkit-0.0.3/venv/Lib/site-packages/bleach/__init__.py
dist/pydevtoolkit-0.0.3/pydevtoolkit-0.0.3/venv/Lib/site-packages/bleach/callbacks.py
dist/pydevtoolkit-0.0.3/pydevtoolkit-0.0.3/venv/Lib/site-packages/bleach/html5lib_shim.py
dist/pydevtoolkit-0.0.3/pydevtoolkit-0.0.3/venv/Lib/site-packages/bleach/linkifier.py
dist/pydevtoolkit-0.0.3/pydevtoolkit-0.0.3/venv/Lib/site-packages/bleach/sanitizer.py
dist/pydevtoolkit-0.0.3/pydevtoolkit-0.0.3/venv/Lib/site-packages/bleach/utils.py
dist/pydevtoolkit-0.0.3/pydevtoolkit-0.0.3/venv/Lib/site-packages/bleach-3.2.1.dist-info/top_level.txt
dist/pydevtoolkit-0.0.3/pydevtoolkit-0.0.3/venv/Lib/site-packages/bleach/_vendor/__init__.py
dist/pydevtoolkit-0.0.3/pydevtoolkit-0.0.3/venv/Lib/site-packages/bleach/_vendor/vendor.txt
dist/pydevtoolkit-0.0.3/pydevtoolkit-0.0.3/venv/Lib/site-packages/bleach/_vendor/html5lib/__init__.py
dist/pydevtoolkit-0.0.3/pydevtoolkit-0.0.3/venv/Lib/site-packages/bleach/_vendor/html5lib/_ihatexml.py
dist/pydevtoolkit-0.0.3/pydevtoolkit-0.0.3/venv/Lib/site-packages/bleach/_vendor/html5lib/_inputstream.py
dist/pydevtoolkit-0.0.3/pydevtoolkit-0.0.3/venv/Lib/site-packages/bleach/_vendor/html5lib/_tokenizer.py
dist/pydevtoolkit-0.0.3/pydevtoolkit-0.0.3/venv/Lib/site-packages/bleach/_vendor/html5lib-1.1.dist-info/top_level.txt
dist/pydevtoolkit-0.0.3/pydevtoolkit-0.0.3/venv/Lib/site-packages/certifi-2020.6.20.dist-info/top_level.txt
dist/pydevtoolkit-0.0.3/pydevtoolkit-0.0.3/venv/Lib/site-packages/chardet-3.0.4.dist-info/entry_points.txt
dist/pydevtoolkit-0.0.3/pydevtoolkit-0.0.3/venv/Lib/site-packages/chardet-3.0.4.dist-info/top_level.txt
dist/pydevtoolkit-0.0.3/pydevtoolkit-0.0.3/venv/Lib/site-packages/colorama-0.4.4.dist-info/LICENSE.txt
dist/pydevtoolkit-0.0.3/pydevtoolkit-0.0.3/venv/Lib/site-packages/colorama-0.4.4.dist-info/top_level.txt
dist/pydevtoolkit-0.0.3/pydevtoolkit-0.0.3/venv/Lib/site-packages/docutils-0.16.dist-info/COPYING.txt
dist/pydevtoolkit-0.0.3/pydevtoolkit-0.0.3/venv/Lib/site-packages/docutils-0.16.dist-info/top_level.txt
dist/pydevtoolkit-0.0.3/pydevtoolkit-0.0.3/venv/Lib/site-packages/idna-2.10.dist-info/top_level.txt
dist/pydevtoolkit-0.0.3/pydevtoolkit-0.0.3/venv/Lib/site-packages/keyring-21.4.0.dist-info/entry_points.txt
dist/pydevtoolkit-0.0.3/pydevtoolkit-0.0.3/venv/Lib/site-packages/keyring-21.4.0.dist-info/top_level.txt
dist/pydevtoolkit-0.0.3/pydevtoolkit-0.0.3/venv/Lib/site-packages/packaging-20.4.dist-info/top_level.txt
dist/pydevtoolkit-0.0.3/pydevtoolkit-0.0.3/venv/Lib/site-packages/pip-20.2.4.dist-info/LICENSE.txt
dist/pydevtoolkit-0.0.3/pydevtoolkit-0.0.3/venv/Lib/site-packages/pip-20.2.4.dist-info/entry_points.txt
dist/pydevtoolkit-0.0.3/pydevtoolkit-0.0.3/venv/Lib/site-packages/pip-20.2.4.dist-info/top_level.txt
dist/pydevtoolkit-0.0.3/pydevtoolkit-0.0.3/venv/Lib/site-packages/pkginfo-1.6.1.dist-info/LICENSE.txt
dist/pydevtoolkit-0.0.3/pydevtoolkit-0.0.3/venv/Lib/site-packages/pkginfo-1.6.1.dist-info/entry_points.txt
dist/pydevtoolkit-0.0.3/pydevtoolkit-0.0.3/venv/Lib/site-packages/pkginfo-1.6.1.dist-info/top_level.txt
dist/pydevtoolkit-0.0.3/pydevtoolkit-0.0.3/venv/Lib/site-packages/pyparsing-2.4.7.dist-info/top_level.txt
dist/pydevtoolkit-0.0.3/pydevtoolkit-0.0.3/venv/Lib/site-packages/pywin32_ctypes-0.2.0.dist-info/LICENSE.txt
dist/pydevtoolkit-0.0.3/pydevtoolkit-0.0.3/venv/Lib/site-packages/pywin32_ctypes-0.2.0.dist-info/top_level.txt
dist/pydevtoolkit-0.0.3/pydevtoolkit-0.0.3/venv/Lib/site-packages/readme_renderer-28.0.dist-info/entry_points.txt
dist/pydevtoolkit-0.0.3/pydevtoolkit-0.0.3/venv/Lib/site-packages/readme_renderer-28.0.dist-info/top_level.txt
dist/pydevtoolkit-0.0.3/pydevtoolkit-0.0.3/venv/Lib/site-packages/requests-2.24.0.dist-info/LICENSE.txt
dist/pydevtoolkit-0.0.3/pydevtoolkit-0.0.3/venv/Lib/site-packages/requests-2.24.0.dist-info/top_level.txt
dist/pydevtoolkit-0.0.3/pydevtoolkit-0.0.3/venv/Lib/site-packages/requests_toolbelt-0.9.1.dist-info/top_level.txt
dist/pydevtoolkit-0.0.3/pydevtoolkit-0.0.3/venv/Lib/site-packages/rfc3986-1.4.0.dist-info/top_level.txt
dist/pydevtoolkit-0.0.3/pydevtoolkit-0.0.3/venv/Lib/site-packages/setuptools-50.3.2.dist-info/dependency_links.txt
dist/pydevtoolkit-0.0.3/pydevtoolkit-0.0.3/venv/Lib/site-packages/setuptools-50.3.2.dist-info/entry_points.txt
dist/pydevtoolkit-0.0.3/pydevtoolkit-0.0.3/venv/Lib/site-packages/setuptools-50.3.2.dist-info/top_level.txt
