Metadata-Version: 1.1
Name: pydevtoolkit
Version: 0.0.4
Summary: A python toolkit for developers
Home-page: UNKNOWN
Author: Snowflake
Author-email: snowflake@fake.com
License: MIT
Keywords: py_tk
Platform: UNKNOWN
Classifier: Development Status :: 5 - Production/Stable
Classifier: Intended Audience :: Education
Classifier: Operating System :: Microsoft :: Windows :: Windows 8.1
Classifier: License :: OSI Approved :: MIT License
Classifier: Programming Language :: Python :: 3
